{"config": {"view": {"continuousWidth": 300, "continuousHeight": 300}}, "layer": [{"data": {"name": "data-bcae43748801615ae30a93486077dd11"}, "mark": {"type": "rule", "size": 2}, "encoding": {"color": {"field": "color", "legend": null, "scale": null, "type": "nominal"}, "tooltip": [{"field": "mz", "format": ".4f", "title": "m/z", "type": "quantitative"}, {"field": "intensity", "format": ".1%", "title": "Intensity", "type": "quantitative"}], "x": {"axis": {"grid": true, "title": "m/z", "titleFontStyle": "italic"}, "field": "mz", "scale": {"nice": true, "padding": 5}, "type": "quantitative"}, "y": {"axis": {"format": "%", "grid": true, "title": "Intensity"}, "field": "intensity", "scale": {"nice": true}, "type": "quantitative"}}}, {"data": {"name": "data-934c4baff6b76a174fd00bbe29bb5455"}, "mark": {"type": "rule", "size": 2}, "encoding": {"color": {"field": "color", "legend": null, "scale": null, "type": "nominal"}, "tooltip": [{"field": "mz", "format": ".4f", "title": "m/z", "type": "quantitative"}, {"field": "intensity", "format": ".1%", "title": "Intensity", "type": "quantitative"}, {"field": "fragment", "title": "Fragment", "type": "nominal"}, {"field": "mz_delta", "title": "m/z deviation", "type": "nominal"}], "x": {"axis": {"grid": true, "title": "m/z", "titleFontStyle": "italic"}, "field": "mz", "scale": {"nice": true, "padding": 5}, "type": "quantitative"}, "y": {"axis": {"format": "%", "grid": true, "title": "Intensity"}, "field": "intensity", "scale": {"nice": true}, "type": "quantitative"}}}, {"data": {"name": "data-934c4baff6b76a174fd00bbe29bb5455"}, "mark": {"type": "text", "align": "left", "angle": 270, "baseline": "middle", "dx": 5}, "encoding": {"color": {"field": "color", "legend": null, "scale": null, "type": "nominal"}, "text": {"field": "fragment", "type": "nominal"}, "tooltip": [{"field": "mz", "format": ".4f", "title": "m/z", "type": "quantitative"}, {"field": "intensity", "format": ".1%", "title": "Intensity", "type": "quantitative"}, {"field": "fragment", "title": "Fragment", "type": "nominal"}, {"field": "mz_delta", "title": "m/z deviation", "type": "nominal"}], "x": {"axis": {"grid": true, "title": "m/z", "titleFontStyle": "italic"}, "field": "mz", "scale": {"nice": true, "padding": 5}, "type": "quantitative"}, "y": {"axis": {"format": "%", "grid": true, "title": "Intensity"}, "field": "intensity", "scale": {"nice": true}, "type": "quantitative"}}}], "height": 400, "width": 640, "$schema": "https://vega.github.io/schema/vega-lite/v6.1.0.json", "datasets": {"data-bcae43748801615ae30a93486077dd11": [{"mz": 83.06068420410156, "intensity": 0.10643626749515533, "fragment": "", "mz_delta": null, "color": "#212121"}, {"mz": 84.04513549804688, "intensity": 0.15948055684566498, "fragment": "", "mz_delta": null, "color": "#212121"}, {"mz": 84.08135986328125, "intensity": 0.40656813979148865, "fragment": "", "mz_delta": null, "color": "#212121"}, {"mz": 101.0712890625, "intensity": 0.19759231805801392, "fragment": "", "mz_delta": null, "color": "#212121"}, {"mz": 102.05531311035156, "intensity": 0.10700903087854385, "fragment": "", "mz_delta": null, "color": "#212121"}, {"mz": 110.07145690917969, "intensity": 0.7268104553222656, "fragment": "", "mz_delta": null, "color": "#212121"}, {"mz": 112.08721160888672, "intensity": 0.24824245274066925, "fragment": "", "mz_delta": null, "color": "#212121"}, {"mz": 115.08665466308594, "intensity": 0.17421133816242218, "fragment": "", "mz_delta": null, "color": "#212121"}, {"mz": 126.09104919433594, "intensity": 0.15318483114242554, "fragment": "", "mz_delta": null, "color": "#212121"}, {"mz": 129.1022186279297, "intensity": 0.4172465205192566, "fragment": "", "mz_delta": null, "color": "#212121"}, {"mz": 129.138427734375, "intensity": 0.17054955661296844, "fragment": "", "mz_delta": null, "color": "#212121"}, {"mz": 136.07568359375, "intensity": 0.10870859771966934, "fragment": "", "mz_delta": null, "color": "#212121"}, {"mz": 138.06613159179688, "intensity": 0.12256339937448502, "fragment": "", "mz_delta": null, "color": "#212121"}, {"mz": 140.08193969726562, "intensity": 0.19764697551727295, "fragment": "", "mz_delta": null, "color": "#212121"}, {"mz": 143.11727905273438, "intensity": 0.1957542449235916, "fragment": "", "mz_delta": null, "color": "#212121"}, {"mz": 147.11212158203125, "intensity": 0.18067339062690735, "fragment": "", "mz_delta": null, "color": "#212121"}, {"mz": 155.0922393798828, "intensity": 0.12364886701107025, "fragment": "", "mz_delta": null, "color": "#212121"}, {"mz": 156.076416015625, "intensity": 0.2223772257566452, "fragment": "", "mz_delta": null, "color": "#212121"}, {"mz": 158.09237670898438, "intensity": 0.15108291804790497, "fragment": "", "mz_delta": null, "color": "#212121"}, {"mz": 169.0967559814453, "intensity": 0.12354103475809097, "fragment": "", "mz_delta": null, "color": "#212121"}, {"mz": 174.0867919921875, "intensity": 0.11803945153951645, "fragment": "", "mz_delta": null, "color": "#212121"}, {"mz": 193.1077423095703, "intensity": 0.1492483913898468, "fragment": "", "mz_delta": null, "color": "#212121"}, {"mz": 202.0819854736328, "intensity": 0.22812379896640778, "fragment": "", "mz_delta": null, "color": "#212121"}, {"mz": 204.07565307617188, "intensity": 0.10041298717260361, "fragment": "", "mz_delta": null, "color": "#212121"}, {"mz": 207.08709716796875, "intensity": 0.2363530993461609, "fragment": "", "mz_delta": null, "color": "#212121"}, {"mz": 211.11947631835938, "intensity": 0.1097027137875557, "fragment": "", "mz_delta": null, "color": "#212121"}, {"mz": 212.13894653320312, "intensity": 0.15556272864341736, "fragment": "", "mz_delta": null, "color": "#212121"}, {"mz": 221.10247802734375, "intensity": 0.17593257129192352, "fragment": "", "mz_delta": null, "color": "#212121"}, {"mz": 224.11376953125, "intensity": 0.12883858382701874, "fragment": "", "mz_delta": null, "color": "#212121"}, {"mz": 226.15463256835938, "intensity": 0.10152462869882584, "fragment": "", "mz_delta": null, "color": "#212121"}, {"mz": 235.08221435546875, "intensity": 0.23816631734371185, "fragment": "", "mz_delta": null, "color": "#212121"}, {"mz": 239.1141357421875, "intensity": 0.23377461731433868, "fragment": "", "mz_delta": null, "color": "#212121"}, {"mz": 244.16505432128906, "intensity": 0.21051007509231567, "fragment": "", "mz_delta": null, "color": "#212121"}, {"mz": 252.10935974121094, "intensity": 0.5085946917533875, "fragment": "", "mz_delta": null, "color": "#212121"}, {"mz": 252.1322021484375, "intensity": 0.10110493004322052, "fragment": "", "mz_delta": null, "color": "#212121"}, {"mz": 253.091552734375, "intensity": 0.12490899860858917, "fragment": "", "mz_delta": null, "color": "#212121"}, {"mz": 253.17715454101562, "intensity": 0.3315236568450928, "fragment": "", "mz_delta": null, "color": "#212121"}, {"mz": 255.1446075439453, "intensity": 0.41548386216163635, "fragment": "", "mz_delta": null, "color": "#212121"}, {"mz": 257.12420654296875, "intensity": 0.1030350774526596, "fragment": "", "mz_delta": null, "color": "#212121"}, {"mz": 266.1615905761719, "intensity": 0.291568398475647, "fragment": "", "mz_delta": null, "color": "#212121"}, {"mz": 284.17169189453125, "intensity": 0.4283383786678314, "fragment": "", "mz_delta": null, "color": "#212121"}, {"mz": 287.20819091796875, "intensity": 0.11740715801715851, "fragment": "", "mz_delta": null, "color": "#212121"}, {"mz": 291.11798095703125, "intensity": 0.17986233532428741, "fragment": "", "mz_delta": null, "color": "#212121"}, {"mz": 304.160400390625, "intensity": 0.11014224588871002, "fragment": "", "mz_delta": null, "color": "#212121"}, {"mz": 315.20220947265625, "intensity": 0.24718914926052094, "fragment": "", "mz_delta": null, "color": "#212121"}, {"mz": 323.1737976074219, "intensity": 0.10283871740102768, "fragment": "", "mz_delta": null, "color": "#212121"}, {"mz": 339.13885498046875, "intensity": 0.143711656332016, "fragment": "", "mz_delta": null, "color": "#212121"}, {"mz": 367.2086486816406, "intensity": 0.10173024982213974, "fragment": "", "mz_delta": null, "color": "#212121"}, {"mz": 377.15887451171875, "intensity": 0.13506928086280823, "fragment": "", "mz_delta": null, "color": "#212121"}, {"mz": 385.21954345703125, "intensity": 0.24775390326976776, "fragment": "", "mz_delta": null, "color": "#212121"}, {"mz": 393.18780517578125, "intensity": 0.25904223322868347, "fragment": "", "mz_delta": null, "color": "#212121"}, {"mz": 403.1710205078125, "intensity": 0.10160460323095322, "fragment": "", "mz_delta": null, "color": "#212121"}, {"mz": 411.1976623535156, "intensity": 0.2483043372631073, "fragment": "", "mz_delta": null, "color": "#212121"}, {"mz": 412.25848388671875, "intensity": 0.10125744342803955, "fragment": "", "mz_delta": null, "color": "#212121"}, {"mz": 421.182861328125, "intensity": 0.3005286455154419, "fragment": "", "mz_delta": null, "color": "#212121"}, {"mz": 439.1935729980469, "intensity": 0.3927520215511322, "fragment": "", "mz_delta": null, "color": "#212121"}, {"mz": 448.1812744140625, "intensity": 0.11003073304891586, "fragment": "", "mz_delta": null, "color": "#212121"}, {"mz": 455.2947998046875, "intensity": 0.12998554110527039, "fragment": "", "mz_delta": null, "color": "#212121"}, {"mz": 456.25860595703125, "intensity": 0.16151314973831177, "fragment": "", "mz_delta": null, "color": "#212121"}, {"mz": 456.74725341796875, "intensity": 0.12472067773342133, "fragment": "", "mz_delta": null, "color": "#212121"}, {"mz": 457.19903564453125, "intensity": 0.29085904359817505, "fragment": "", "mz_delta": null, "color": "#212121"}, {"mz": 475.73919677734375, "intensity": 0.10123813897371292, "fragment": "", "mz_delta": null, "color": "#212121"}, {"mz": 483.29315185546875, "intensity": 0.3222971260547638, "fragment": "", "mz_delta": null, "color": "#212121"}, {"mz": 490.240478515625, "intensity": 0.11649928241968155, "fragment": "", "mz_delta": null, "color": "#212121"}, {"mz": 507.2353515625, "intensity": 0.16863596439361572, "fragment": "", "mz_delta": null, "color": "#212121"}, {"mz": 512.752685546875, "intensity": 0.11724527180194855, "fragment": "", "mz_delta": null, "color": "#212121"}, {"mz": 513.3095703125, "intensity": 0.10429046303033829, "fragment": "", "mz_delta": null, "color": "#212121"}, {"mz": 524.210693359375, "intensity": 0.18265753984451294, "fragment": "", "mz_delta": null, "color": "#212121"}, {"mz": 527.3319091796875, "intensity": 0.10998029261827469, "fragment": "", "mz_delta": null, "color": "#212121"}, {"mz": 540.225830078125, "intensity": 0.14759808778762817, "fragment": "", "mz_delta": null, "color": "#212121"}, {"mz": 540.31640625, "intensity": 0.36348795890808105, "fragment": "", "mz_delta": null, "color": "#212121"}, {"mz": 541.319580078125, "intensity": 0.13228832185268402, "fragment": "", "mz_delta": null, "color": "#212121"}, {"mz": 549.272705078125, "intensity": 0.24276915192604065, "fragment": "", "mz_delta": null, "color": "#212121"}, {"mz": 550.2022705078125, "intensity": 0.1178293228149414, "fragment": "", "mz_delta": null, "color": "#212121"}, {"mz": 556.343994140625, "intensity": 0.4241671562194824, "fragment": "", "mz_delta": null, "color": "#212121"}, {"mz": 557.250244140625, "intensity": 0.11399123072624207, "fragment": "", "mz_delta": null, "color": "#212121"}, {"mz": 557.3452758789062, "intensity": 0.1508680284023285, "fragment": "", "mz_delta": null, "color": "#212121"}, {"mz": 562.3055419921875, "intensity": 0.14721333980560303, "fragment": "", "mz_delta": null, "color": "#212121"}, {"mz": 566.3294067382812, "intensity": 0.44409117102622986, "fragment": "", "mz_delta": null, "color": "#212121"}, {"mz": 567.2821655273438, "intensity": 0.5189292430877686, "fragment": "", "mz_delta": null, "color": "#212121"}, {"mz": 567.7713623046875, "intensity": 0.1953095644712448, "fragment": "", "mz_delta": null, "color": "#212121"}, {"mz": 568.2064208984375, "intensity": 0.2575361132621765, "fragment": "", "mz_delta": null, "color": "#212121"}, {"mz": 568.2957763671875, "intensity": 0.11042921245098114, "fragment": "", "mz_delta": null, "color": "#212121"}, {"mz": 575.7945556640625, "intensity": 0.12142908573150635, "fragment": "", "mz_delta": null, "color": "#212121"}, {"mz": 576.2823486328125, "intensity": 0.37753769755363464, "fragment": "", "mz_delta": null, "color": "#212121"}, {"mz": 662.3424682617188, "intensity": 0.11736366152763367, "fragment": "", "mz_delta": null, "color": "#212121"}, {"mz": 669.27978515625, "intensity": 0.12252424657344818, "fragment": "", "mz_delta": null, "color": "#212121"}, {"mz": 683.3096313476562, "intensity": 0.20824839174747467, "fragment": "", "mz_delta": null, "color": "#212121"}, {"mz": 870.4035034179688, "intensity": 0.17632164061069489, "fragment": "", "mz_delta": null, "color": "#212121"}, {"mz": 881.3804931640625, "intensity": 0.17262932658195496, "fragment": "", "mz_delta": null, "color": "#212121"}, {"mz": 884.431396484375, "intensity": 0.10292420536279678, "fragment": "", "mz_delta": null, "color": "#212121"}, {"mz": 899.3892822265625, "intensity": 0.24457044899463654, "fragment": "", "mz_delta": null, "color": "#212121"}, {"mz": 909.4544067382812, "intensity": 0.10282257944345474, "fragment": "", "mz_delta": null, "color": "#212121"}, {"mz": 917.3982543945312, "intensity": 0.1121288388967514, "fragment": "", "mz_delta": null, "color": "#212121"}, {"mz": 970.043701171875, "intensity": 0.1000661626458168, "fragment": "", "mz_delta": null, "color": "#212121"}, {"mz": 1062.5006103515625, "intensity": 0.30762213468551636, "fragment": "", "mz_delta": null, "color": "#212121"}, {"mz": 1110.51708984375, "intensity": 0.45916664600372314, "fragment": "", "mz_delta": null, "color": "#212121"}, {"mz": 1152.5400390625, "intensity": 1.0, "fragment": "", "mz_delta": null, "color": "#212121"}], "data-934c4baff6b76a174fd00bbe29bb5455": [{"mz": 157.10855102539062, "intensity": 0.33645880222320557, "fragment": "b1", "mz_delta": "1.0ppm", "color": "#1976D2"}, {"mz": 175.11904907226562, "intensity": 0.3317154049873352, "fragment": "y1", "mz_delta": "0.6ppm", "color": "#D32F2F"}, {"mz": 254.160400390625, "intensity": 0.34151193499565125, "fragment": "b2", "mz_delta": "-3.0ppm", "color": "#1976D2"}, {"mz": 272.1718444824219, "intensity": 0.2420218288898468, "fragment": "y2", "mz_delta": "0.5ppm", "color": "#D32F2F"}, {"mz": 369.1875915527344, "intensity": 0.5033606886863708, "fragment": "b3", "mz_delta": "-1.4ppm", "color": "#1976D2"}, {"mz": 541.2364501953125, "intensity": 0.35371851921081543, "fragment": "b5", "mz_delta": "-0.1ppm", "color": "#1976D2"}, {"mz": 612.2705078125, "intensity": 0.10247302055358887, "fragment": "b6", "mz_delta": "-5.1ppm", "color": "#1976D2"}, {"mz": 629.3377685546875, "intensity": 0.527380645275116, "fragment": "y6", "mz_delta": "1.9ppm", "color": "#D32F2F"}, {"mz": 770.3419189453125, "intensity": 0.19471155107021332, "fragment": "b8", "mz_delta": "-1.1ppm", "color": "#1976D2"}, {"mz": 801.3828125, "intensity": 0.5478774309158325, "fragment": "y8", "mz_delta": "-2.7ppm", "color": "#D32F2F"}, {"mz": 898.4000854492188, "intensity": 0.3244994878768921, "fragment": "b9", "mz_delta": "-1.4ppm", "color": "#1976D2"}, {"mz": 916.416259765625, "intensity": 0.27773210406303406, "fragment": "y9", "mz_delta": "4.8ppm", "color": "#D32F2F"}, {"mz": 1013.46142578125, "intensity": 0.41171538829803467, "fragment": "y10", "mz_delta": "-3.2ppm", "color": "#D32F2F"}]}}