{"config": {"view": {"continuousWidth": 300, "continuousHeight": 300}}, "layer": [{"data": {"name": "data-19c2c06271e052ca11f992281b99a659"}, "mark": {"type": "rule", "size": 2}, "encoding": {"color": {"field": "color", "legend": null, "scale": null, "type": "nominal"}, "tooltip": [{"field": "mz", "format": ".4f", "title": "m/z", "type": "quantitative"}, {"field": "intensity", "format": ".1%", "title": "Intensity", "type": "quantitative"}], "x": {"axis": {"grid": true, "title": "m/z", "titleFontStyle": "italic"}, "field": "mz", "scale": {"nice": true, "padding": 5}, "type": "quantitative"}, "y": {"axis": {"format": "%", "grid": true, "title": "Intensity"}, "field": "intensity", "scale": {"nice": true}, "type": "quantitative"}}}, {"data": {"name": "data-bb67c40d46f4fbaf8cb680d5d18c9f69"}, "mark": {"type": "rule", "size": 2}, "encoding": {"color": {"field": "color", "legend": null, "scale": null, "type": "nominal"}, "tooltip": [{"field": "mz", "format": ".4f", "title": "m/z", "type": "quantitative"}, {"field": "intensity", "format": ".1%", "title": "Intensity", "type": "quantitative"}, {"field": "fragment", "title": "Fragment", "type": "nominal"}, {"field": "mz_delta", "title": "m/z deviation", "type": "nominal"}], "x": {"axis": {"grid": true, "title": "m/z", "titleFontStyle": "italic"}, "field": "mz", "scale": {"nice": true, "padding": 5}, "type": "quantitative"}, "y": {"axis": {"format": "%", "grid": true, "title": "Intensity"}, "field": "intensity", "scale": {"nice": true}, "type": "quantitative"}}}, {"data": {"name": "data-bb67c40d46f4fbaf8cb680d5d18c9f69"}, "mark": {"type": "text", "align": "left", "angle": 270, "baseline": "middle", "dx": 5}, "encoding": {"color": {"field": "color", "legend": null, "scale": null, "type": "nominal"}, "text": {"field": "fragment", "type": "nominal"}, "tooltip": [{"field": "mz", "format": ".4f", "title": "m/z", "type": "quantitative"}, {"field": "intensity", "format": ".1%", "title": "Intensity", "type": "quantitative"}, {"field": "fragment", "title": "Fragment", "type": "nominal"}, {"field": "mz_delta", "title": "m/z deviation", "type": "nominal"}], "x": {"axis": {"grid": true, "title": "m/z", "titleFontStyle": "italic"}, "field": "mz", "scale": {"nice": true, "padding": 5}, "type": "quantitative"}, "y": {"axis": {"format": "%", "grid": true, "title": "Intensity"}, "field": "intensity", "scale": {"nice": true}, "type": "quantitative"}}}], "height": 400, "width": 640, "$schema": "https://vega.github.io/schema/vega-lite/v6.1.0.json", "datasets": {"data-19c2c06271e052ca11f992281b99a659": [{"mz": 92.60910034179688, "intensity": 0.3725023865699768, "fragment": "", "mz_delta": null, "color": "#212121"}, {"mz": 106.68038940429688, "intensity": 0.38289690017700195, "fragment": "", "mz_delta": null, "color": "#212121"}, {"mz": 110.07159423828125, "intensity": 0.5469959378242493, "fragment": "", "mz_delta": null, "color": "#212121"}, {"mz": 129.10238647460938, "intensity": 0.787674605846405, "fragment": "", "mz_delta": null, "color": "#212121"}, {"mz": 133.043212890625, "intensity": 0.5770173072814941, "fragment": "", "mz_delta": null, "color": "#212121"}, {"mz": 152.30215454101562, "intensity": 0.3901064991950989, "fragment": "", "mz_delta": null, "color": "#212121"}, {"mz": 188.47471618652344, "intensity": 0.39601731300354004, "fragment": "", "mz_delta": null, "color": "#212121"}, {"mz": 275.08038330078125, "intensity": 0.6080219149589539, "fragment": "", "mz_delta": null, "color": "#212121"}, {"mz": 448.07373046875, "intensity": 0.145194873213768, "fragment": "", "mz_delta": null, "color": "#212121"}, {"mz": 448.0827331542969, "intensity": 0.2007531076669693, "fragment": "", "mz_delta": null, "color": "#212121"}, {"mz": 448.09173583984375, "intensity": 0.22335819900035858, "fragment": "", "mz_delta": null, "color": "#212121"}, {"mz": 448.1007385253906, "intensity": 0.2071434110403061, "fragment": "", "mz_delta": null, "color": "#212121"}, {"mz": 448.1097412109375, "intensity": 0.15616096556186676, "fragment": "", "mz_delta": null, "color": "#212121"}, {"mz": 463.58087158203125, "intensity": 0.15925556421279907, "fragment": "", "mz_delta": null, "color": "#212121"}, {"mz": 463.5903625488281, "intensity": 0.214103564620018, "fragment": "", "mz_delta": null, "color": "#212121"}, {"mz": 463.5998229980469, "intensity": 0.22935549914836884, "fragment": "", "mz_delta": null, "color": "#212121"}, {"mz": 463.6092834472656, "intensity": 0.2033025026321411, "fragment": "", "mz_delta": null, "color": "#212121"}, {"mz": 463.6187438964844, "intensity": 0.14682801067829132, "fragment": "", "mz_delta": null, "color": "#212121"}, {"mz": 469.6524353027344, "intensity": 0.17286963760852814, "fragment": "", "mz_delta": null, "color": "#212121"}, {"mz": 469.6620788574219, "intensity": 0.22436802089214325, "fragment": "", "mz_delta": null, "color": "#212121"}, {"mz": 469.6717529296875, "intensity": 0.2374335676431656, "fragment": "", "mz_delta": null, "color": "#212121"}, {"mz": 469.681396484375, "intensity": 0.20801715552806854, "fragment": "", "mz_delta": null, "color": "#212121"}, {"mz": 469.6910705566406, "intensity": 0.14236828684806824, "fragment": "", "mz_delta": null, "color": "#212121"}, {"mz": 508.6859436035156, "intensity": 0.16314341127872467, "fragment": "", "mz_delta": null, "color": "#212121"}, {"mz": 508.7294921875, "intensity": 0.16402970254421234, "fragment": "", "mz_delta": null, "color": "#212121"}, {"mz": 509.17608642578125, "intensity": 0.1932108998298645, "fragment": "", "mz_delta": null, "color": "#212121"}, {"mz": 509.1869812011719, "intensity": 0.23407317698001862, "fragment": "", "mz_delta": null, "color": "#212121"}, {"mz": 509.2087707519531, "intensity": 0.1441333144903183, "fragment": "", "mz_delta": null, "color": "#212121"}, {"mz": 540.1689453125, "intensity": 0.19187739491462708, "fragment": "", "mz_delta": null, "color": "#212121"}, {"mz": 540.1808471679688, "intensity": 0.2895600199699402, "fragment": "", "mz_delta": null, "color": "#212121"}, {"mz": 540.1927490234375, "intensity": 0.3517194390296936, "fragment": "", "mz_delta": null, "color": "#212121"}, {"mz": 540.2166137695312, "intensity": 0.3082845211029053, "fragment": "", "mz_delta": null, "color": "#212121"}, {"mz": 540.228515625, "intensity": 0.22134298086166382, "fragment": "", "mz_delta": null, "color": "#212121"}, {"mz": 540.2404174804688, "intensity": 0.1378343403339386, "fragment": "", "mz_delta": null, "color": "#212121"}, {"mz": 580.2225952148438, "intensity": 0.327239066362381, "fragment": "", "mz_delta": null, "color": "#212121"}, {"mz": 580.2490844726562, "intensity": 0.3476172089576721, "fragment": "", "mz_delta": null, "color": "#212121"}, {"mz": 580.2623291015625, "intensity": 0.2735515832901001, "fragment": "", "mz_delta": null, "color": "#212121"}, {"mz": 607.7476806640625, "intensity": 0.21746808290481567, "fragment": "", "mz_delta": null, "color": "#212121"}, {"mz": 607.7619018554688, "intensity": 0.2464684545993805, "fragment": "", "mz_delta": null, "color": "#212121"}, {"mz": 607.776123046875, "intensity": 0.23373420536518097, "fragment": "", "mz_delta": null, "color": "#212121"}, {"mz": 653.2462158203125, "intensity": 0.1884438693523407, "fragment": "", "mz_delta": null, "color": "#212121"}, {"mz": 653.2620849609375, "intensity": 0.23394298553466797, "fragment": "", "mz_delta": null, "color": "#212121"}, {"mz": 653.2778930664062, "intensity": 0.24991756677627563, "fragment": "", "mz_delta": null, "color": "#212121"}, {"mz": 693.2785034179688, "intensity": 0.17977425456047058, "fragment": "", "mz_delta": null, "color": "#212121"}, {"mz": 693.2958374023438, "intensity": 0.25591301918029785, "fragment": "", "mz_delta": null, "color": "#212121"}, {"mz": 693.3131713867188, "intensity": 0.30983567237854004, "fragment": "", "mz_delta": null, "color": "#212121"}, {"mz": 693.3477783203125, "intensity": 0.2906542420387268, "fragment": "", "mz_delta": null, "color": "#212121"}, {"mz": 693.3651123046875, "intensity": 0.2163955420255661, "fragment": "", "mz_delta": null, "color": "#212121"}, {"mz": 734.5883178710938, "intensity": 0.19887052476406097, "fragment": "", "mz_delta": null, "color": "#212121"}, {"mz": 734.607177734375, "intensity": 0.25224676728248596, "fragment": "", "mz_delta": null, "color": "#212121"}, {"mz": 734.6260986328125, "intensity": 0.26693782210350037, "fragment": "", "mz_delta": null, "color": "#212121"}, {"mz": 734.6449584960938, "intensity": 0.23985034227371216, "fragment": "", "mz_delta": null, "color": "#212121"}, {"mz": 734.6638793945312, "intensity": 0.1774493306875229, "fragment": "", "mz_delta": null, "color": "#212121"}, {"mz": 831.0115966796875, "intensity": 0.19243575632572174, "fragment": "", "mz_delta": null, "color": "#212121"}, {"mz": 831.0343627929688, "intensity": 0.25524255633354187, "fragment": "", "mz_delta": null, "color": "#212121"}, {"mz": 831.0570678710938, "intensity": 0.27919667959213257, "fragment": "", "mz_delta": null, "color": "#212121"}, {"mz": 831.0797729492188, "intensity": 0.2574746012687683, "fragment": "", "mz_delta": null, "color": "#212121"}, {"mz": 831.1025390625, "intensity": 0.19538716971874237, "fragment": "", "mz_delta": null, "color": "#212121"}, {"mz": 887.35546875, "intensity": 0.20531119406223297, "fragment": "", "mz_delta": null, "color": "#212121"}, {"mz": 887.3805541992188, "intensity": 0.24302558600902557, "fragment": "", "mz_delta": null, "color": "#212121"}, {"mz": 887.4307250976562, "intensity": 0.23566967248916626, "fragment": "", "mz_delta": null, "color": "#212121"}, {"mz": 887.455810546875, "intensity": 0.19655026495456696, "fragment": "", "mz_delta": null, "color": "#212121"}, {"mz": 934.625244140625, "intensity": 0.19352345168590546, "fragment": "", "mz_delta": null, "color": "#212121"}, {"mz": 934.6524047851562, "intensity": 0.25694510340690613, "fragment": "", "mz_delta": null, "color": "#212121"}, {"mz": 934.6795043945312, "intensity": 0.2784697413444519, "fragment": "", "mz_delta": null, "color": "#212121"}, {"mz": 934.7066040039062, "intensity": 0.25648072361946106, "fragment": "", "mz_delta": null, "color": "#212121"}, {"mz": 934.7337036132812, "intensity": 0.20053471624851227, "fragment": "", "mz_delta": null, "color": "#212121"}, {"mz": 1016.3849487304688, "intensity": 0.3156411647796631, "fragment": "", "mz_delta": null, "color": "#212121"}, {"mz": 1016.4076538085938, "intensity": 0.34266984462738037, "fragment": "", "mz_delta": null, "color": "#212121"}, {"mz": 1016.4293823242188, "intensity": 0.3103284239768982, "fragment": "", "mz_delta": null, "color": "#212121"}], "data-bb67c40d46f4fbaf8cb680d5d18c9f69": [{"mz": 147.11233520507812, "intensity": 0.528391420841217, "fragment": "y1", "mz_delta": "-3.2ppm", "color": "#D32F2F"}, {"mz": 307.1442565917969, "intensity": 1.0, "fragment": "y2", "mz_delta": "2.6ppm", "color": "#D32F2F"}, {"mz": 509.1978759765625, "intensity": 0.18640033900737762, "fragment": "y4", "mz_delta": "-8.9ppm", "color": "#D32F2F"}, {"mz": 540.2046508789062, "intensity": 0.3583574593067169, "fragment": "b5", "mz_delta": "-0.4ppm", "color": "#1976D2"}, {"mz": 580.23583984375, "intensity": 0.36793866753578186, "fragment": "y5", "mz_delta": "-6.4ppm", "color": "#D32F2F"}, {"mz": 653.2937622070312, "intensity": 0.22737915813922882, "fragment": "b6", "mz_delta": "7.4ppm", "color": "#1976D2"}, {"mz": 693.3304443359375, "intensity": 0.3239736258983612, "fragment": "y6", "mz_delta": "9.9ppm", "color": "#D32F2F"}, {"mz": 887.4056396484375, "intensity": 0.25366514921188354, "fragment": "y8", "mz_delta": "1.9ppm", "color": "#D32F2F"}]}}