{"config": {"view": {"continuousWidth": 300, "continuousHeight": 300}}, "layer": [{"data": {"name": "data-2dafec0796cfa6972654da788890e692"}, "mark": {"type": "rule", "size": 2}, "encoding": {"color": {"field": "color", "legend": null, "scale": null, "type": "nominal"}, "tooltip": [{"field": "mz", "format": ".4f", "title": "m/z", "type": "quantitative"}, {"field": "intensity", "format": ".1%", "title": "Intensity", "type": "quantitative"}], "x": {"axis": {"grid": true, "title": "m/z", "titleFontStyle": "italic"}, "field": "mz", "scale": {"nice": true, "padding": 5}, "type": "quantitative"}, "y": {"axis": {"format": "%", "grid": true, "title": "Intensity"}, "field": "intensity", "scale": {"nice": true}, "type": "quantitative"}}, "transform": [{"filter": "(datum.color === '#212121' && showBase) || (datum.color === '#D32F2F' && showY) || (datum.color === '#1976D2' && showB)"}]}, {"data": {"name": "data-a3e02149a2a82d6666a2ec8cf8b9c488"}, "mark": {"type": "rule", "size": 2}, "encoding": {"color": {"field": "color", "legend": null, "scale": null, "type": "nominal"}, "tooltip": [{"field": "mz", "format": ".4f", "title": "m/z", "type": "quantitative"}, {"field": "intensity", "format": ".1%", "title": "Intensity", "type": "quantitative"}, {"field": "fragment", "title": "Fragment", "type": "nominal"}, {"field": "mz_delta", "title": "m/z deviation", "type": "nominal"}], "x": {"axis": {"grid": true, "title": "m/z", "titleFontStyle": "italic"}, "field": "mz", "scale": {"nice": true, "padding": 5}, "type": "quantitative"}, "y": {"axis": {"format": "%", "grid": true, "title": "Intensity"}, "field": "intensity", "scale": {"nice": true}, "type": "quantitative"}}, "transform": [{"filter": "(datum.color === '#212121' && showBase) || (datum.color === '#D32F2F' && showY) || (datum.color === '#1976D2' && showB)"}]}, {"data": {"name": "data-a3e02149a2a82d6666a2ec8cf8b9c488"}, "mark": {"type": "text", "align": "left", "angle": 270, "baseline": "middle", "dx": 5}, "encoding": {"color": {"field": "color", "legend": null, "scale": null, "type": "nominal"}, "text": {"field": "fragment", "type": "nominal"}, "tooltip": [{"field": "mz", "format": ".4f", "title": "m/z", "type": "quantitative"}, {"field": "intensity", "format": ".1%", "title": "Intensity", "type": "quantitative"}, {"field": "fragment", "title": "Fragment", "type": "nominal"}, {"field": "mz_delta", "title": "m/z deviation", "type": "nominal"}], "x": {"axis": {"grid": true, "title": "m/z", "titleFontStyle": "italic"}, "field": "mz", "scale": {"nice": true, "padding": 5}, "type": "quantitative"}, "y": {"axis": {"format": "%", "grid": true, "title": "Intensity"}, "field": "intensity", "scale": {"nice": true}, "type": "quantitative"}}, "transform": [{"filter": "(datum.color === '#212121' && showBase) || (datum.color === '#D32F2F' && showY) || (datum.color === '#1976D2' && showB)"}]}], "params": [{"name": "showBase", "bind": {"input": "checkbox"}, "value": true}, {"name": "showY", "bind": {"input": "checkbox"}, "value": true}, {"name": "showB", "bind": {"input": "checkbox"}, "value": true}], "width": "container", "$schema": "https://vega.github.io/schema/vega-lite/v6.1.0.json", "datasets": {"data-2dafec0796cfa6972654da788890e692": [{"mz": 129.10272216796875, "intensity": 0.565046489238739, "fragment": "", "mz_delta": null, "color": "#212121"}, {"mz": 155.05413818359375, "intensity": 0.46835240721702576, "fragment": "", "mz_delta": null, "color": "#212121"}, {"mz": 188.10284423828125, "intensity": 0.47970056533813477, "fragment": "", "mz_delta": null, "color": "#212121"}, {"mz": 244.09344482421875, "intensity": 0.5627774000167847, "fragment": "", "mz_delta": null, "color": "#212121"}, {"mz": 313.10845947265625, "intensity": 0.4461440443992615, "fragment": "", "mz_delta": null, "color": "#212121"}, {"mz": 315.8910217285156, "intensity": 0.4077671468257904, "fragment": "", "mz_delta": null, "color": "#212121"}, {"mz": 488.9698791503906, "intensity": 0.17773319780826569, "fragment": "", "mz_delta": null, "color": "#212121"}, {"mz": 488.9801330566406, "intensity": 0.24238206446170807, "fragment": "", "mz_delta": null, "color": "#212121"}, {"mz": 488.9903869628906, "intensity": 0.26709282398223877, "fragment": "", "mz_delta": null, "color": "#212121"}, {"mz": 489.0006408691406, "intensity": 0.24093644320964813, "fragment": "", "mz_delta": null, "color": "#212121"}, {"mz": 489.01092529296875, "intensity": 0.16760912537574768, "fragment": "", "mz_delta": null, "color": "#212121"}, {"mz": 518.2666625976562, "intensity": 0.1775788515806198, "fragment": "", "mz_delta": null, "color": "#212121"}, {"mz": 518.27783203125, "intensity": 0.2506627142429352, "fragment": "", "mz_delta": null, "color": "#212121"}, {"mz": 518.3002319335938, "intensity": 0.28517842292785645, "fragment": "", "mz_delta": null, "color": "#212121"}, {"mz": 518.3114624023438, "intensity": 0.23377951979637146, "fragment": "", "mz_delta": null, "color": "#212121"}, {"mz": 768.7911376953125, "intensity": 0.22453196346759796, "fragment": "", "mz_delta": null, "color": "#212121"}, {"mz": 768.8114013671875, "intensity": 0.29173514246940613, "fragment": "", "mz_delta": null, "color": "#212121"}, {"mz": 768.8316040039062, "intensity": 0.31582754850387573, "fragment": "", "mz_delta": null, "color": "#212121"}, {"mz": 768.851806640625, "intensity": 0.2917380928993225, "fragment": "", "mz_delta": null, "color": "#212121"}, {"mz": 768.8720703125, "intensity": 0.22393211722373962, "fragment": "", "mz_delta": null, "color": "#212121"}, {"mz": 785.3524169921875, "intensity": 0.1824091374874115, "fragment": "", "mz_delta": null, "color": "#212121"}, {"mz": 785.3734741210938, "intensity": 0.3474279046058655, "fragment": "", "mz_delta": null, "color": "#212121"}, {"mz": 785.3941650390625, "intensity": 0.4111971855163574, "fragment": "", "mz_delta": null, "color": "#212121"}, {"mz": 785.4150390625, "intensity": 0.39472681283950806, "fragment": "", "mz_delta": null, "color": "#212121"}, {"mz": 785.4359130859375, "intensity": 0.30454114079475403, "fragment": "", "mz_delta": null, "color": "#212121"}, {"mz": 786.3555297851562, "intensity": 0.2588231563568115, "fragment": "", "mz_delta": null, "color": "#212121"}, {"mz": 786.37646484375, "intensity": 0.2579394578933716, "fragment": "", "mz_delta": null, "color": "#212121"}, {"mz": 786.3973999023438, "intensity": 0.2346208691596985, "fragment": "", "mz_delta": null, "color": "#212121"}, {"mz": 786.4182739257812, "intensity": 0.1660962849855423, "fragment": "", "mz_delta": null, "color": "#212121"}, {"mz": 844.3255615234375, "intensity": 0.18600431084632874, "fragment": "", "mz_delta": null, "color": "#212121"}, {"mz": 844.348876953125, "intensity": 0.4889701306819916, "fragment": "", "mz_delta": null, "color": "#212121"}, {"mz": 844.3721313476562, "intensity": 0.7599233388900757, "fragment": "", "mz_delta": null, "color": "#212121"}, {"mz": 844.3953857421875, "intensity": 0.9625860452651978, "fragment": "", "mz_delta": null, "color": "#212121"}, {"mz": 844.4419555664062, "intensity": 0.8190808892250061, "fragment": "", "mz_delta": null, "color": "#212121"}, {"mz": 844.4652709960938, "intensity": 0.5742422938346863, "fragment": "", "mz_delta": null, "color": "#212121"}, {"mz": 844.488525390625, "intensity": 0.28065094351768494, "fragment": "", "mz_delta": null, "color": "#212121"}, {"mz": 1014.3947143554688, "intensity": 0.2067796289920807, "fragment": "", "mz_delta": null, "color": "#212121"}, {"mz": 1014.4254150390625, "intensity": 0.30814129114151, "fragment": "", "mz_delta": null, "color": "#212121"}, {"mz": 1014.4560546875, "intensity": 0.3769935965538025, "fragment": "", "mz_delta": null, "color": "#212121"}, {"mz": 1014.4866943359375, "intensity": 0.39164605736732483, "fragment": "", "mz_delta": null, "color": "#212121"}, {"mz": 1014.517333984375, "intensity": 0.3462817072868347, "fragment": "", "mz_delta": null, "color": "#212121"}, {"mz": 1014.5479736328125, "intensity": 0.25639602541923523, "fragment": "", "mz_delta": null, "color": "#212121"}, {"mz": 1078.38427734375, "intensity": 0.2816337049007416, "fragment": "", "mz_delta": null, "color": "#212121"}, {"mz": 1078.4178466796875, "intensity": 0.45647498965263367, "fragment": "", "mz_delta": null, "color": "#212121"}, {"mz": 1078.451416015625, "intensity": 0.6810835003852844, "fragment": "", "mz_delta": null, "color": "#212121"}, {"mz": 1078.5186767578125, "intensity": 0.6087772846221924, "fragment": "", "mz_delta": null, "color": "#212121"}, {"mz": 1078.55224609375, "intensity": 0.4205425977706909, "fragment": "", "mz_delta": null, "color": "#212121"}, {"mz": 1078.5858154296875, "intensity": 0.24323150515556335, "fragment": "", "mz_delta": null, "color": "#212121"}, {"mz": 1079.4263916015625, "intensity": 0.13276030123233795, "fragment": "", "mz_delta": null, "color": "#212121"}, {"mz": 1169.05712890625, "intensity": 0.23550115525722504, "fragment": "", "mz_delta": null, "color": "#212121"}, {"mz": 1169.0950927734375, "intensity": 0.316011905670166, "fragment": "", "mz_delta": null, "color": "#212121"}, {"mz": 1169.1329345703125, "intensity": 0.34645822644233704, "fragment": "", "mz_delta": null, "color": "#212121"}, {"mz": 1169.1708984375, "intensity": 0.32010790705680847, "fragment": "", "mz_delta": null, "color": "#212121"}, {"mz": 1169.2088623046875, "intensity": 0.24365535378456116, "fragment": "", "mz_delta": null, "color": "#212121"}, {"mz": 1231.3524169921875, "intensity": 0.22780285775661469, "fragment": "", "mz_delta": null, "color": "#212121"}, {"mz": 1231.3934326171875, "intensity": 0.3174687922000885, "fragment": "", "mz_delta": null, "color": "#212121"}, {"mz": 1231.434326171875, "intensity": 0.36399582028388977, "fragment": "", "mz_delta": null, "color": "#212121"}, {"mz": 1231.475341796875, "intensity": 0.3471029996871948, "fragment": "", "mz_delta": null, "color": "#212121"}, {"mz": 1231.516357421875, "intensity": 0.26756051182746887, "fragment": "", "mz_delta": null, "color": "#212121"}], "data-a3e02149a2a82d6666a2ec8cf8b9c488": [{"mz": 147.11160278320312, "intensity": 0.4817274212837219, "fragment": "y1", "mz_delta": "-8.2ppm", "color": "#D32F2F"}, {"mz": 216.0977783203125, "intensity": 0.8602295517921448, "fragment": "b2", "mz_delta": "-0.5ppm", "color": "#1976D2"}, {"mz": 346.20965576171875, "intensity": 0.49583593010902405, "fragment": "y3", "mz_delta": "3.4ppm", "color": "#D32F2F"}, {"mz": 518.2890625, "intensity": 0.2917530834674835, "fragment": "y5", "mz_delta": "-8.2ppm", "color": "#D32F2F"}, {"mz": 844.418701171875, "intensity": 1.0, "fragment": "y9", "mz_delta": "3.3ppm", "color": "#D32F2F"}, {"mz": 1078.485107421875, "intensity": 0.7292495369911194, "fragment": "y11", "mz_delta": "1.6ppm", "color": "#D32F2F"}, {"mz": 1079.392822265625, "intensity": 0.10481809079647064, "fragment": "b11", "mz_delta": "-1.6ppm", "color": "#1976D2"}]}}